pykirill/__init__.py
pykirill/__main__.py
pykirill/association.py
pykirill/cli.py
pykirill/moods.py
pykirill/plotting.py
pykirill/transforms.py
pykirill/version.py
pykirill-2024.3.1.dist-info/LICENSE.md
pykirill-2024.3.1.dist-info/METADATA
pykirill-2024.3.1.dist-info/WHEEL
pykirill-2024.3.1.dist-info/entry_points.txt
pykirill-2024.3.1.dist-info/top_level.txt
pykirill-2024.3.1.dist-info/RECORD
