Metadata-Version: 2.1
Name: pykirill
Version: 2024.3.1
Summary: 🐗 A portable collection of functions for scientific exploration
Author-email: Kirill Denisov <kirill.denisov@gero.ai>
Maintainer-email: Kirill Denisov <kirill.denisov@gero.ai>
License: MIT License
Project-URL: Homepage, https://kirilledition.github.io/pykirill/
Project-URL: Documentation, https://kirilledition.github.io/pykirill/
Project-URL: Repository, https://github.com/kirilledition/pykirill
Classifier: Programming Language :: Python :: 3.10
Classifier: Programming Language :: Python :: 3.11
Classifier: Programming Language :: Python :: 3.12
Classifier: Programming Language :: Python :: 3.13
Classifier: License :: OSI Approved :: MIT License
Classifier: Operating System :: OS Independent
Classifier: Topic :: Scientific/Engineering
Requires-Python: >=3.10
License-File: LICENSE.md
Requires-Dist: numpy
Requires-Dist: scipy
Requires-Dist: matplotlib
Requires-Dist: seaborn
Requires-Dist: pandas
Requires-Dist: scikit-learn
Requires-Dist: tqdm
Provides-Extra: development
Requires-Dist: pytest; extra == "development"
Requires-Dist: ruff; extra == "development"
Requires-Dist: mypy; extra == "development"
Requires-Dist: ipython; extra == "development"
Requires-Dist: build; extra == "development"
Provides-Extra: documentation
Requires-Dist: mkdocs-material; extra == "documentation"
Requires-Dist: mkdocstrings[python]; extra == "documentation"
Requires-Dist: mkdocs-jupyter; extra == "documentation"
